vocode/__init__.py
vocode/account_connections/__init__.py
vocode/account_connections/client.py
vocode/actions/__init__.py
vocode/actions/client.py
vocode/agents/__init__.py
vocode/agents/client.py
vocode/calls/__init__.py
vocode/calls/client.py
vocode/calls/types/__init__.py
vocode/calls/types/create_call_request_agent.py
vocode/calls/types/create_call_request_on_no_human_answer.py
vocode/client.py
vocode/core/__init__.py
vocode/core/api_error.py
vocode/core/client_wrapper.py
vocode/core/datetime_utils.py
vocode/core/file.py
vocode/core/http_client.py
vocode/core/jsonable_encoder.py
vocode/core/pydantic_utilities.py
vocode/core/query_encoder.py
vocode/core/remove_none_from_dict.py
vocode/core/request_options.py
vocode/core/serialization.py
vocode/environment.py
vocode/errors/__init__.py
vocode/errors/unprocessable_entity_error.py
vocode/numbers/__init__.py
vocode/numbers/client.py
vocode/numbers/types/__init__.py
vocode/numbers/types/buy_phone_number_request_inbound_agent.py
vocode/numbers/types/buy_phone_number_request_telephony_provider.py
vocode/numbers/types/link_phone_number_request_inbound_agent.py
vocode/numbers/types/update_number_request_example_context.py
vocode/numbers/types/update_number_request_inbound_agent.py
vocode/numbers/types/update_number_request_label.py
vocode/numbers/types/update_number_request_outbound_only.py
vocode/prompts/__init__.py
vocode/prompts/client.py
vocode/py.typed
vocode/types/__init__.py
vocode/types/account_connection_page.py
vocode/types/account_connection_page_items_item.py
vocode/types/account_connection_params_request.py
vocode/types/account_connection_response_model.py
vocode/types/account_connection_update_params_request.py
vocode/types/action_page.py
vocode/types/action_page_items_item.py
vocode/types/action_params_request.py
vocode/types/action_response_model.py
vocode/types/action_update_params_request.py
vocode/types/add_to_conference_action.py
vocode/types/add_to_conference_action_action_trigger.py
vocode_api-0.0.48.dist-info/METADATA
vocode_api-0.0.48.dist-info/WHEEL
vocode_api-0.0.48.dist-info/RECORD
